parmot/__init__.py
parmot/client.py
parmot/schemas.py
parmot/stripe_integration.py
parmot/usage.py
parmot/providers/__init__.py
parmot/providers/anthropic.py
parmot/providers/cohere.py
parmot/providers/openai.py
parmot-0.1.1.dist-info/licenses/LICENSE
parmot-0.1.1.dist-info/METADATA
parmot-0.1.1.dist-info/WHEEL
parmot-0.1.1.dist-info/top_level.txt
parmot-0.1.1.dist-info/RECORD
