Metadata-Version: 2.4
Name: parmot
Version: 0.1.1
Summary: Parmot client SDK with LLM usage tracking and provider wrappers.
Author-email: Emmett McFarlane <emmett@thepi.pe>
License-Expression: MIT
Project-URL: Homepage, https://parmot.com
Project-URL: Repository, https://github.com/emcf/parmot
Project-URL: Issues, https://github.com/emcf/parmot/issues
Keywords: llm,usage,tracking,sdk,openai,anthropic,cohere
Classifier: Programming Language :: Python :: 3
Classifier: Programming Language :: Python :: 3 :: Only
Classifier: Programming Language :: Python :: 3.9
Classifier: Programming Language :: Python :: 3.10
Classifier: Programming Language :: Python :: 3.11
Classifier: Programming Language :: Python :: 3.12
Classifier: Typing :: Typed
Requires-Python: >=3.9
License-File: LICENSE
Requires-Dist: requests>=2.31.0
Provides-Extra: openai
Requires-Dist: openai; extra == "openai"
Provides-Extra: anthropic
Requires-Dist: anthropic; extra == "anthropic"
Provides-Extra: cohere
Requires-Dist: cohere; extra == "cohere"
Provides-Extra: dev
Requires-Dist: mypy>=1.10.0; extra == "dev"
Requires-Dist: pytest>=7.4.0; extra == "dev"
Requires-Dist: build>=1.2.1; extra == "dev"
Requires-Dist: twine>=5.1.0; extra == "dev"
Requires-Dist: ruff>=0.5.0; extra == "dev"
Requires-Dist: openai; extra == "dev"
Requires-Dist: anthropic; extra == "dev"
Requires-Dist: cohere; extra == "dev"
Requires-Dist: black; extra == "dev"
Dynamic: license-file
